{"resourceSpans":[{"resource":{"attributes":[{"key":"service.name","value":{"stringValue":"hipster-shop.hipster-shop"}}]},"scopeSpans":[{"scope":{},"spans":[{"traceId":"bf945dfbdec5b312f04efc143cbdd3f1","spanId":"db15b7a374f1b08e","parentSpanId":"bdf06e7d67390e3d","name":"cartservice.hipster-shop.svc.cluster.local:7070/*","kind":2,"startTimeUnixNano":"1748005370902013000","endTimeUnixNano":"1748005370907047000","attributes":[{"key":"node_id","value":{"stringValue":"sidecar~10.16.0.40~cartservice-6c4cd797ff-tv4t9.hipster-shop~hipster-shop.svc.cluster.local"}},{"key":"zone","value":{"stringValue":"europe-west3-a"}},{"key":"guid:x-request-id","value":{"stringValue":"32682c37-b48a-94fc-8c2b-e5a233bc9f8d"}},{"key":"http.url","value":{"stringValue":"http://cartservice:7070/hipstershop.CartService/GetCart"}},{"key":"http.method","value":{"stringValue":"POST"}},{"key":"downstream_cluster","value":{"stringValue":"-"}},{"key":"user_agent","value":{"stringValue":"grpc-go/1.29.1"}},{"key":"http.protocol","value":{"stringValue":"HTTP/2"}},{"key":"peer.address","value":{"stringValue":"10.16.0.45"}},{"key":"grpc.path","value":{"stringValue":"/hipstershop.CartService/GetCart"}},{"key":"grpc.authority","value":{"stringValue":"cartservice:7070"}},{"key":"grpc.content_type","value":{"stringValue":"application/grpc"}},{"key":"request_size","value":{"stringValue":"43"}},{"key":"response_size","value":{"stringValue":"75"}},{"key":"component","value":{"stringValue":"proxy"}},{"key":"upstream_cluster","value":{"stringValue":"inbound|7070||"}},{"key":"upstream_cluster.name","value":{"stringValue":"inbound|7070||;"}},{"key":"http.status_code","value":{"stringValue":"200"}},{"key":"response_flags","value":{"stringValue":"-"}},{"key":"istio.canonical_service","value":{"stringValue":"cartservice"}},{"key":"istio.canonical_revision","value":{"stringValue":"1.0.0"}},{"key":"istio.mesh_id","value":{"stringValue":"cluster.local"}},{"key":"istio.cluster_id","value":{"stringValue":"Kubernetes"}},{"key":"istio.namespace","value":{"stringValue":"hipster-shop"}},{"key":"grpc.status_code","value":{"stringValue":"0"}}],"status":{}},{"traceId":"a11d75e0166ca941ff143b4f8f71b050","spanId":"9423346ca18ae42d","parentSpanId":"476659222e498022","name":"cartservice.hipster-shop.svc.cluster.local:7070/*","kind":2,"startTimeUnixNano":"1748005371104405000","endTimeUnixNano":"1748005371107734000","attributes":[{"key":"node_id","value":{"stringValue":"sidecar~10.16.0.40~cartservice-6c4cd797ff-tv4t9.hipster-shop~hipster-shop.svc.cluster.local"}},{"key":"zone","value":{"stringValue":"europe-west3-a"}},{"key":"guid:x-request-id","value":{"stringValue":"24cd328d-7df7-9f30-8522-d828852025c2"}},{"key":"http.url","value":{"stringValue":"http://cartservice:7070/hipstershop.CartService/GetCart"}},{"key":"http.method","value":{"stringValue":"POST"}},{"key":"downstream_cluster","value":{"stringValue":"-"}},{"key":"user_agent","value":{"stringValue":"grpc-go/1.29.1"}},{"key":"http.protocol","value":{"stringValue":"HTTP/2"}},{"key":"peer.address","value":{"stringValue":"10.16.0.45"}},{"key":"grpc.path","value":{"stringValue":"/hipstershop.CartService/GetCart"}},{"key":"grpc.authority","value":{"stringValue":"cartservice:7070"}},{"key":"grpc.content_type","value":{"stringValue":"application/grpc"}},{"key":"request_size","value":{"stringValue":"43"}},{"key":"response_size","value":{"stringValue":"75"}},{"key":"component","value":{"stringValue":"proxy"}},{"key":"upstream_cluster","value":{"stringValue":"inbound|7070||"}},{"key":"upstream_cluster.name","value":{"stringValue":"inbound|7070||;"}},{"key":"http.status_code","value":{"stringValue":"200"}},{"key":"response_flags","value":{"stringValue":"-"}},{"key":"istio.canonical_service","value":{"stringValue":"cartservice"}},{"key":"istio.canonical_revision","value":{"stringValue":"1.0.0"}},{"key":"istio.mesh_id","value":{"stringValue":"cluster.local"}},{"key":"istio.cluster_id","value":{"stringValue":"Kubernetes"}},{"key":"istio.namespace","value":{"stringValue":"hipster-shop"}},{"key":"grpc.status_code","value":{"stringValue":"0"}}],"status":{}},{"traceId":"98f22c418565c75a6b4446cddd1d50c0","spanId":"ac1ebf427120012a","parentSpanId":"943d73e068e808c2","name":"cartservice.hipster-shop.svc.cluster.local:7070/*","kind":2,"startTimeUnixNano":"1748005371166142000","endTimeUnixNano":"1748005371170448000","attributes":[{"key":"node_id","value":{"stringValue":"sidecar~10.16.0.40~cartservice-6c4cd797ff-tv4t9.hipster-shop~hipster-shop.svc.cluster.local"}},{"key":"zone","value":{"stringValue":"europe-west3-a"}},{"key":"guid:x-request-id","value":{"stringValue":"2df03232-e14d-94fd-81c1-c2bd992b3fb7"}},{"key":"http.url","value":{"stringValue":"http://cartservice:7070/hipstershop.CartService/GetCart"}},{"key":"http.method","value":{"stringValue":"POST"}},{"key":"downstream_cluster","value":{"stringValue":"-"}},{"key":"user_agent","value":{"stringValue":"grpc-go/1.29.1"}},{"key":"http.protocol","value":{"stringValue":"HTTP/2"}},{"key":"peer.address","value":{"stringValue":"10.16.0.45"}},{"key":"grpc.path","value":{"stringValue":"/hipstershop.CartService/GetCart"}},{"key":"grpc.authority","value":{"stringValue":"cartservice:7070"}},{"key":"grpc.content_type","value":{"stringValue":"application/grpc"}},{"key":"request_size","value":{"stringValue":"43"}},{"key":"response_size","value":{"stringValue":"75"}},{"key":"component","value":{"stringValue":"proxy"}},{"key":"upstream_cluster","value":{"stringValue":"inbound|7070||"}},{"key":"upstream_cluster.name","value":{"stringValue":"inbound|7070||;"}},{"key":"http.status_code","value":{"stringValue":"200"}},{"key":"response_flags","value":{"stringValue":"-"}},{"key":"istio.canonical_service","value":{"stringValue":"cartservice"}},{"key":"istio.canonical_revision","value":{"stringValue":"1.0.0"}},{"key":"istio.mesh_id","value":{"stringValue":"cluster.local"}},{"key":"istio.cluster_id","value":{"stringValue":"Kubernetes"}},{"key":"istio.namespace","value":{"stringValue":"hipster-shop"}},{"key":"grpc.status_code","value":{"stringValue":"0"}}],"status":{}},{"traceId":"698947429afeaf23f3e82c74f479b7e1","spanId":"046b944c1155c5a8","parentSpanId":"b762046aec19d02c","name":"cartservice.hipster-shop.svc.cluster.local:7070/*","kind":2,"startTimeUnixNano":"1748005371222406000","endTimeUnixNano":"1748005371227459000","attributes":[{"key":"node_id","value":{"stringValue":"sidecar~10.16.0.40~cartservice-6c4cd797ff-tv4t9.hipster-shop~hipster-shop.svc.cluster.local"}},{"key":"zone","value":{"stringValue":"europe-west3-a"}},{"key":"guid:x-request-id","value":{"stringValue":"b5cded31-22c0-9957-b446-ba7453ce0d8b"}},{"key":"http.url","value":{"stringValue":"http://cartservice:7070/hipstershop.CartService/GetCart"}},{"key":"http.method","value":{"stringValue":"POST"}},{"key":"downstream_cluster","value":{"stringValue":"-"}},{"key":"user_agent","value":{"stringValue":"grpc-go/1.29.1"}},{"key":"http.protocol","value":{"stringValue":"HTTP/2"}},{"key":"peer.address","value":{"stringValue":"10.16.0.45"}},{"key":"grpc.path","value":{"stringValue":"/hipstershop.CartService/GetCart"}},{"key":"grpc.authority","value":{"stringValue":"cartservice:7070"}},{"key":"grpc.content_type","value":{"stringValue":"application/grpc"}},{"key":"request_size","value":{"stringValue":"43"}},{"key":"response_size","value":{"stringValue":"75"}},{"key":"component","value":{"stringValue":"proxy"}},{"key":"upstream_cluster","value":{"stringValue":"inbound|7070||"}},{"key":"upstream_cluster.name","value":{"stringValue":"inbound|7070||;"}},{"key":"http.status_code","value":{"stringValue":"200"}},{"key":"response_flags","value":{"stringValue":"-"}},{"key":"istio.canonical_service","value":{"stringValue":"cartservice"}},{"key":"istio.canonical_revision","value":{"stringValue":"1.0.0"}},{"key":"istio.mesh_id","value":{"stringValue":"cluster.local"}},{"key":"istio.cluster_id","value":{"stringValue":"Kubernetes"}},{"key":"istio.namespace","value":{"stringValue":"hipster-shop"}},{"key":"grpc.status_code","value":{"stringValue":"0"}}],"status":{}},{"traceId":"99fa7e189a0f5ca4da5d3da96d7c48e0","spanId":"c1864618da044b3a","parentSpanId":"ba2d1efd42bd5f40","name":"cartservice.hipster-shop.svc.cluster.local:7070/*","kind":2,"startTimeUnixNano":"1748005371309078000","endTimeUnixNano":"1748005371313247000","attributes":[{"key":"node_id","value":{"stringValue":"sidecar~10.16.0.40~cartservice-6c4cd797ff-tv4t9.hipster-shop~hipster-shop.svc.cluster.local"}},{"key":"zone","value":{"stringValue":"europe-west3-a"}},{"key":"guid:x-request-id","value":{"stringValue":"ec4a8ec0-d338-9386-bb86-580a6a552124"}},{"key":"http.url","value":{"stringValue":"http://cartservice:7070/hipstershop.CartService/GetCart"}},{"key":"http.method","value":{"stringValue":"POST"}},{"key":"downstream_cluster","value":{"stringValue":"-"}},{"key":"user_agent","value":{"stringValue":"grpc-go/1.29.1"}},{"key":"http.protocol","value":{"stringValue":"HTTP/2"}},{"key":"peer.address","value":{"stringValue":"10.16.0.45"}},{"key":"grpc.path","value":{"stringValue":"/hipstershop.CartService/GetCart"}},{"key":"grpc.authority","value":{"stringValue":"cartservice:7070"}},{"key":"grpc.content_type","value":{"stringValue":"application/grpc"}},{"key":"request_size","value":{"stringValue":"43"}},{"key":"response_size","value":{"stringValue":"75"}},{"key":"component","value":{"stringValue":"proxy"}},{"key":"upstream_cluster","value":{"stringValue":"inbound|7070||"}},{"key":"upstream_cluster.name","value":{"stringValue":"inbound|7070||;"}},{"key":"http.status_code","value":{"stringValue":"200"}},{"key":"response_flags","value":{"stringValue":"-"}},{"key":"istio.canonical_service","value":{"stringValue":"cartservice"}},{"key":"istio.canonical_revision","value":{"stringValue":"1.0.0"}},{"key":"istio.mesh_id","value":{"stringValue":"cluster.local"}},{"key":"istio.cluster_id","value":{"stringValue":"Kubernetes"}},{"key":"istio.namespace","value":{"stringValue":"hipster-shop"}},{"key":"grpc.status_code","value":{"stringValue":"0"}}],"status":{}}]}]}]}