{"resourceSpans":[{"resource":{"attributes":[{"key":"service.name","value":{"stringValue":"hipster-shop.hipster-shop"}}]},"scopeSpans":[{"scope":{},"spans":[{"traceId":"3f3128876670a276b3b7e417c502d16e","spanId":"222883d6fb5f7df9","parentSpanId":"","name":"recommendationservice.hipster-shop.svc.cluster.local:8080/*","kind":3,"startTimeUnixNano":"1748005463048315000","endTimeUnixNano":"1748005463048484000","attributes":[{"key":"node_id","value":{"stringValue":"sidecar~10.16.0.45~frontend-6b55c84d7-2wb7d.hipster-shop~hipster-shop.svc.cluster.local"}},{"key":"zone","value":{"stringValue":"europe-west3-a"}},{"key":"guid:x-request-id","value":{"stringValue":"d3e3564f-bd14-986d-8711-830edf0bb3e4"}},{"key":"http.url","value":{"stringValue":"http://recommendationservice:8080/hipstershop.RecommendationService/ListRecommendations"}},{"key":"http.method","value":{"stringValue":"POST"}},{"key":"downstream_cluster","value":{"stringValue":"-"}},{"key":"user_agent","value":{"stringValue":"grpc-go/1.29.1"}},{"key":"http.protocol","value":{"stringValue":"HTTP/2"}},{"key":"peer.address","value":{"stringValue":"10.16.0.45"}},{"key":"grpc.path","value":{"stringValue":"/hipstershop.RecommendationService/ListRecommendations"}},{"key":"grpc.authority","value":{"stringValue":"recommendationservice:8080"}},{"key":"grpc.content_type","value":{"stringValue":"application/grpc"}},{"key":"request_size","value":{"stringValue":"0"}},{"key":"response_size","value":{"stringValue":"0"}},{"key":"component","value":{"stringValue":"proxy"}},{"key":"upstream_cluster","value":{"stringValue":"outbound|8080||recommendationservice.hipster-shop.svc.cluster.local"}},{"key":"upstream_cluster.name","value":{"stringValue":"outbound|8080||recommendationservice.hipster-shop.svc.cluster.local;"}},{"key":"http.status_code","value":{"stringValue":"200"}},{"key":"response_flags","value":{"stringValue":"UH"}},{"key":"istio.canonical_service","value":{"stringValue":"frontend"}},{"key":"istio.canonical_revision","value":{"stringValue":"1.0.0"}},{"key":"istio.cluster_id","value":{"stringValue":"Kubernetes"}},{"key":"istio.mesh_id","value":{"stringValue":"cluster.local"}},{"key":"istio.namespace","value":{"stringValue":"hipster-shop"}},{"key":"grpc.status_code","value":{"stringValue":"14"}},{"key":"grpc.message","value":{"stringValue":"no healthy upstream"}},{"key":"error","value":{"stringValue":"true"}}],"status":{"code":2}},{"traceId":"1b5a34dccdc95a10ff2feac9a7ce3f4c","spanId":"c0395dbc05fdaa46","parentSpanId":"","name":"recommendationservice.hipster-shop.svc.cluster.local:8080/*","kind":3,"startTimeUnixNano":"1748005463048528000","endTimeUnixNano":"1748005463048690000","attributes":[{"key":"node_id","value":{"stringValue":"sidecar~10.16.0.45~frontend-6b55c84d7-2wb7d.hipster-shop~hipster-shop.svc.cluster.local"}},{"key":"zone","value":{"stringValue":"europe-west3-a"}},{"key":"guid:x-request-id","value":{"stringValue":"72999ad1-b2f9-9751-b2c1-a6797a49aa71"}},{"key":"http.url","value":{"stringValue":"http://recommendationservice:8080/hipstershop.RecommendationService/ListRecommendations"}},{"key":"http.method","value":{"stringValue":"POST"}},{"key":"downstream_cluster","value":{"stringValue":"-"}},{"key":"user_agent","value":{"stringValue":"grpc-go/1.29.1"}},{"key":"http.protocol","value":{"stringValue":"HTTP/2"}},{"key":"peer.address","value":{"stringValue":"10.16.0.45"}},{"key":"grpc.path","value":{"stringValue":"/hipstershop.RecommendationService/ListRecommendations"}},{"key":"grpc.authority","value":{"stringValue":"recommendationservice:8080"}},{"key":"grpc.content_type","value":{"stringValue":"application/grpc"}},{"key":"request_size","value":{"stringValue":"0"}},{"key":"response_size","value":{"stringValue":"0"}},{"key":"component","value":{"stringValue":"proxy"}},{"key":"upstream_cluster","value":{"stringValue":"outbound|8080||recommendationservice.hipster-shop.svc.cluster.local"}},{"key":"upstream_cluster.name","value":{"stringValue":"outbound|8080||recommendationservice.hipster-shop.svc.cluster.local;"}},{"key":"http.status_code","value":{"stringValue":"200"}},{"key":"response_flags","value":{"stringValue":"UH"}},{"key":"istio.namespace","value":{"stringValue":"hipster-shop"}},{"key":"istio.canonical_revision","value":{"stringValue":"1.0.0"}},{"key":"istio.canonical_service","value":{"stringValue":"frontend"}},{"key":"istio.cluster_id","value":{"stringValue":"Kubernetes"}},{"key":"istio.mesh_id","value":{"stringValue":"cluster.local"}},{"key":"grpc.status_code","value":{"stringValue":"14"}},{"key":"grpc.message","value":{"stringValue":"no healthy upstream"}},{"key":"error","value":{"stringValue":"true"}}],"status":{"code":2}},{"traceId":"54e20b1b94ebeee6106d5def514db2b6","spanId":"a0308ca5d4d5988e","parentSpanId":"","name":"productcatalogservice.hipster-shop.svc.cluster.local:3550/*","kind":3,"startTimeUnixNano":"1748005462082786000","endTimeUnixNano":"1748005463097068000","attributes":[{"key":"node_id","value":{"stringValue":"sidecar~10.16.0.45~frontend-6b55c84d7-2wb7d.hipster-shop~hipster-shop.svc.cluster.local"}},{"key":"zone","value":{"stringValue":"europe-west3-a"}},{"key":"guid:x-request-id","value":{"stringValue":"bd62459c-4284-96eb-8b29-39ea63edeb1a"}},{"key":"http.url","value":{"stringValue":"http://productcatalogservice:3550/hipstershop.ProductCatalogService/GetProduct"}},{"key":"http.method","value":{"stringValue":"POST"}},{"key":"downstream_cluster","value":{"stringValue":"-"}},{"key":"user_agent","value":{"stringValue":"grpc-go/1.29.1"}},{"key":"http.protocol","value":{"stringValue":"HTTP/2"}},{"key":"peer.address","value":{"stringValue":"10.16.0.45"}},{"key":"grpc.path","value":{"stringValue":"/hipstershop.ProductCatalogService/GetProduct"}},{"key":"grpc.authority","value":{"stringValue":"productcatalogservice:3550"}},{"key":"grpc.content_type","value":{"stringValue":"application/grpc"}},{"key":"request_size","value":{"stringValue":"17"}},{"key":"response_size","value":{"stringValue":"158"}},{"key":"component","value":{"stringValue":"proxy"}},{"key":"upstream_cluster","value":{"stringValue":"outbound|3550||productcatalogservice.hipster-shop.svc.cluster.local"}},{"key":"upstream_cluster.name","value":{"stringValue":"outbound|3550||productcatalogservice.hipster-shop.svc.cluster.local;"}},{"key":"http.status_code","value":{"stringValue":"200"}},{"key":"response_flags","value":{"stringValue":"-"}},{"key":"istio.canonical_revision","value":{"stringValue":"1.0.0"}},{"key":"istio.canonical_service","value":{"stringValue":"frontend"}},{"key":"istio.mesh_id","value":{"stringValue":"cluster.local"}},{"key":"istio.cluster_id","value":{"stringValue":"Kubernetes"}},{"key":"istio.namespace","value":{"stringValue":"hipster-shop"}},{"key":"grpc.status_code","value":{"stringValue":"0"}},{"key":"grpc.message","value":{"stringValue":""}}],"status":{}},{"traceId":"1c7175e50065d50b39193a4af38550b6","spanId":"cb887e3b22ed351d","parentSpanId":"","name":"productcatalogservice.hipster-shop.svc.cluster.local:3550/*","kind":3,"startTimeUnixNano":"1748005461627726000","endTimeUnixNano":"1748005463097324000","attributes":[{"key":"node_id","value":{"stringValue":"sidecar~10.16.0.45~frontend-6b55c84d7-2wb7d.hipster-shop~hipster-shop.svc.cluster.local"}},{"key":"zone","value":{"stringValue":"europe-west3-a"}},{"key":"guid:x-request-id","value":{"stringValue":"bfa44194-5f59-9bef-a0ac-d13cd3d50d00"}},{"key":"http.url","value":{"stringValue":"http://productcatalogservice:3550/hipstershop.ProductCatalogService/GetProduct"}},{"key":"http.method","value":{"stringValue":"POST"}},{"key":"downstream_cluster","value":{"stringValue":"-"}},{"key":"user_agent","value":{"stringValue":"grpc-go/1.29.1"}},{"key":"http.protocol","value":{"stringValue":"HTTP/2"}},{"key":"peer.address","value":{"stringValue":"10.16.0.45"}},{"key":"grpc.path","value":{"stringValue":"/hipstershop.ProductCatalogService/GetProduct"}},{"key":"grpc.authority","value":{"stringValue":"productcatalogservice:3550"}},{"key":"grpc.content_type","value":{"stringValue":"application/grpc"}},{"key":"request_size","value":{"stringValue":"17"}},{"key":"response_size","value":{"stringValue":"147"}},{"key":"component","value":{"stringValue":"proxy"}},{"key":"upstream_cluster","value":{"stringValue":"outbound|3550||productcatalogservice.hipster-shop.svc.cluster.local"}},{"key":"upstream_cluster.name","value":{"stringValue":"outbound|3550||productcatalogservice.hipster-shop.svc.cluster.local;"}},{"key":"http.status_code","value":{"stringValue":"200"}},{"key":"response_flags","value":{"stringValue":"-"}},{"key":"istio.canonical_revision","value":{"stringValue":"1.0.0"}},{"key":"istio.canonical_service","value":{"stringValue":"frontend"}},{"key":"istio.mesh_id","value":{"stringValue":"cluster.local"}},{"key":"istio.cluster_id","value":{"stringValue":"Kubernetes"}},{"key":"istio.namespace","value":{"stringValue":"hipster-shop"}},{"key":"grpc.status_code","value":{"stringValue":"0"}},{"key":"grpc.message","value":{"stringValue":""}}],"status":{}},{"traceId":"738cf21664f4c829b37fb623e83e19d4","spanId":"1103bc2e9127bdad","parentSpanId":"","name":"cartservice.hipster-shop.svc.cluster.local:7070/*","kind":3,"startTimeUnixNano":"1748005463107119000","endTimeUnixNano":"1748005463114741000","attributes":[{"key":"node_id","value":{"stringValue":"sidecar~10.16.0.45~frontend-6b55c84d7-2wb7d.hipster-shop~hipster-shop.svc.cluster.local"}},{"key":"zone","value":{"stringValue":"europe-west3-a"}},{"key":"guid:x-request-id","value":{"stringValue":"25be5421-99af-94d3-abc3-972d077ef900"}},{"key":"http.url","value":{"stringValue":"http://cartservice:7070/hipstershop.CartService/GetCart"}},{"key":"http.method","value":{"stringValue":"POST"}},{"key":"downstream_cluster","value":{"stringValue":"-"}},{"key":"user_agent","value":{"stringValue":"grpc-go/1.29.1"}},{"key":"http.protocol","value":{"stringValue":"HTTP/2"}},{"key":"peer.address","value":{"stringValue":"10.16.0.45"}},{"key":"grpc.path","value":{"stringValue":"/hipstershop.CartService/GetCart"}},{"key":"grpc.authority","value":{"stringValue":"cartservice:7070"}},{"key":"grpc.content_type","value":{"stringValue":"application/grpc"}},{"key":"request_size","value":{"stringValue":"43"}},{"key":"response_size","value":{"stringValue":"5"}},{"key":"component","value":{"stringValue":"proxy"}},{"key":"upstream_cluster","value":{"stringValue":"outbound|7070||cartservice.hipster-shop.svc.cluster.local"}},{"key":"upstream_cluster.name","value":{"stringValue":"outbound|7070||cartservice.hipster-shop.svc.cluster.local;"}},{"key":"http.status_code","value":{"stringValue":"200"}},{"key":"response_flags","value":{"stringValue":"-"}},{"key":"istio.cluster_id","value":{"stringValue":"Kubernetes"}},{"key":"istio.namespace","value":{"stringValue":"hipster-shop"}},{"key":"istio.canonical_service","value":{"stringValue":"frontend"}},{"key":"istio.mesh_id","value":{"stringValue":"cluster.local"}},{"key":"istio.canonical_revision","value":{"stringValue":"1.0.0"}},{"key":"grpc.status_code","value":{"stringValue":"0"}}],"status":{}}]}]}]}