{"resourceSpans":[{"resource":{"attributes":[{"key":"service.name","value":{"stringValue":"hipster-shop.hipster-shop"}}]},"scopeSpans":[{"scope":{},"spans":[{"traceId":"c4d04949951bcccee5103bccea5ab1ff","spanId":"e702c7e208b887f2","parentSpanId":"","name":"currencyservice.hipster-shop.svc.cluster.local:7000/*","kind":3,"startTimeUnixNano":"1748005495075942000","endTimeUnixNano":"1748005495079954000","attributes":[{"key":"node_id","value":{"stringValue":"sidecar~10.16.0.45~frontend-6b55c84d7-2wb7d.hipster-shop~hipster-shop.svc.cluster.local"}},{"key":"zone","value":{"stringValue":"europe-west3-a"}},{"key":"guid:x-request-id","value":{"stringValue":"110720ea-0349-92da-a761-4720e785db0a"}},{"key":"http.url","value":{"stringValue":"http://currencyservice:7000/hipstershop.CurrencyService/GetSupportedCurrencies"}},{"key":"http.method","value":{"stringValue":"POST"}},{"key":"downstream_cluster","value":{"stringValue":"-"}},{"key":"user_agent","value":{"stringValue":"grpc-go/1.29.1"}},{"key":"http.protocol","value":{"stringValue":"HTTP/2"}},{"key":"peer.address","value":{"stringValue":"10.16.0.45"}},{"key":"grpc.path","value":{"stringValue":"/hipstershop.CurrencyService/GetSupportedCurrencies"}},{"key":"grpc.authority","value":{"stringValue":"currencyservice:7000"}},{"key":"grpc.content_type","value":{"stringValue":"application/grpc"}},{"key":"request_size","value":{"stringValue":"5"}},{"key":"response_size","value":{"stringValue":"170"}},{"key":"component","value":{"stringValue":"proxy"}},{"key":"upstream_cluster","value":{"stringValue":"outbound|7000||currencyservice.hipster-shop.svc.cluster.local"}},{"key":"upstream_cluster.name","value":{"stringValue":"outbound|7000||currencyservice.hipster-shop.svc.cluster.local;"}},{"key":"http.status_code","value":{"stringValue":"200"}},{"key":"response_flags","value":{"stringValue":"-"}},{"key":"istio.namespace","value":{"stringValue":"hipster-shop"}},{"key":"istio.canonical_service","value":{"stringValue":"frontend"}},{"key":"istio.mesh_id","value":{"stringValue":"cluster.local"}},{"key":"istio.cluster_id","value":{"stringValue":"Kubernetes"}},{"key":"istio.canonical_revision","value":{"stringValue":"1.0.0"}},{"key":"grpc.status_code","value":{"stringValue":"0"}},{"key":"grpc.message","value":{"stringValue":"OK"}}],"status":{}},{"traceId":"bf0001783f3d13a2377daa3c4b8134d4","spanId":"9a95984e35a0be38","parentSpanId":"c025bb64b90eaa22","name":"frontend.hipster-shop.svc.cluster.local:80/*","kind":2,"startTimeUnixNano":"1748005494079346000","endTimeUnixNano":"1748005495096229000","attributes":[{"key":"node_id","value":{"stringValue":"sidecar~10.16.0.45~frontend-6b55c84d7-2wb7d.hipster-shop~hipster-shop.svc.cluster.local"}},{"key":"zone","value":{"stringValue":"europe-west3-a"}},{"key":"guid:x-request-id","value":{"stringValue":"b9c20406-d9da-9e99-b8eb-fa2a013118d7"}},{"key":"http.url","value":{"stringValue":"http://hipstershop.34.40.36.155.nip.io/cart"}},{"key":"http.method","value":{"stringValue":"POST"}},{"key":"downstream_cluster","value":{"stringValue":"-"}},{"key":"user_agent","value":{"stringValue":"k6/0.40.0 (https://k6.io/)"}},{"key":"http.protocol","value":{"stringValue":"HTTP/1.1"}},{"key":"peer.address","value":{"stringValue":"10.16.0.16"}},{"key":"request_size","value":{"stringValue":"32"}},{"key":"response_size","value":{"stringValue":"0"}},{"key":"component","value":{"stringValue":"proxy"}},{"key":"upstream_cluster","value":{"stringValue":"inbound|8080||"}},{"key":"upstream_cluster.name","value":{"stringValue":"inbound|8080||;"}},{"key":"http.status_code","value":{"stringValue":"302"}},{"key":"response_flags","value":{"stringValue":"-"}},{"key":"istio.mesh_id","value":{"stringValue":"cluster.local"}},{"key":"istio.canonical_service","value":{"stringValue":"frontend"}},{"key":"istio.cluster_id","value":{"stringValue":"Kubernetes"}},{"key":"istio.canonical_revision","value":{"stringValue":"1.0.0"}},{"key":"istio.namespace","value":{"stringValue":"hipster-shop"}}],"status":{}},{"traceId":"0bb7f6c50ffb0ced6fd0e3d50145265c","spanId":"f1776de7e2d22b5e","parentSpanId":"","name":"currencyservice.hipster-shop.svc.cluster.local:7000/*","kind":3,"startTimeUnixNano":"1748005495100688000","endTimeUnixNano":"1748005495104771000","attributes":[{"key":"node_id","value":{"stringValue":"sidecar~10.16.0.45~frontend-6b55c84d7-2wb7d.hipster-shop~hipster-shop.svc.cluster.local"}},{"key":"zone","value":{"stringValue":"europe-west3-a"}},{"key":"guid:x-request-id","value":{"stringValue":"3941accf-b185-9224-9169-7d3774c4bd5c"}},{"key":"http.url","value":{"stringValue":"http://currencyservice:7000/hipstershop.CurrencyService/GetSupportedCurrencies"}},{"key":"http.method","value":{"stringValue":"POST"}},{"key":"downstream_cluster","value":{"stringValue":"-"}},{"key":"user_agent","value":{"stringValue":"grpc-go/1.29.1"}},{"key":"http.protocol","value":{"stringValue":"HTTP/2"}},{"key":"peer.address","value":{"stringValue":"10.16.0.45"}},{"key":"grpc.path","value":{"stringValue":"/hipstershop.CurrencyService/GetSupportedCurrencies"}},{"key":"grpc.authority","value":{"stringValue":"currencyservice:7000"}},{"key":"grpc.content_type","value":{"stringValue":"application/grpc"}},{"key":"request_size","value":{"stringValue":"5"}},{"key":"response_size","value":{"stringValue":"170"}},{"key":"component","value":{"stringValue":"proxy"}},{"key":"upstream_cluster","value":{"stringValue":"outbound|7000||currencyservice.hipster-shop.svc.cluster.local"}},{"key":"upstream_cluster.name","value":{"stringValue":"outbound|7000||currencyservice.hipster-shop.svc.cluster.local;"}},{"key":"http.status_code","value":{"stringValue":"200"}},{"key":"response_flags","value":{"stringValue":"-"}},{"key":"istio.mesh_id","value":{"stringValue":"cluster.local"}},{"key":"istio.canonical_service","value":{"stringValue":"frontend"}},{"key":"istio.cluster_id","value":{"stringValue":"Kubernetes"}},{"key":"istio.canonical_revision","value":{"stringValue":"1.0.0"}},{"key":"istio.namespace","value":{"stringValue":"hipster-shop"}},{"key":"grpc.status_code","value":{"stringValue":"0"}},{"key":"grpc.message","value":{"stringValue":"OK"}}],"status":{}},{"traceId":"2dc596c6ad47ac7f051a3d64e0bdbbd8","spanId":"e4fed81de4442604","parentSpanId":"fc49f4a95661a44d","name":"frontend.hipster-shop.svc.cluster.local:80/*","kind":2,"startTimeUnixNano":"1748005495099029000","endTimeUnixNano":"1748005495115616000","attributes":[{"key":"node_id","value":{"stringValue":"sidecar~10.16.0.45~frontend-6b55c84d7-2wb7d.hipster-shop~hipster-shop.svc.cluster.local"}},{"key":"zone","value":{"stringValue":"europe-west3-a"}},{"key":"guid:x-request-id","value":{"stringValue":"9568086f-2284-9467-a4bc-7d7eda0186fb"}},{"key":"http.url","value":{"stringValue":"http://hipstershop.34.40.36.155.nip.io/cart"}},{"key":"http.method","value":{"stringValue":"GET"}},{"key":"downstream_cluster","value":{"stringValue":"-"}},{"key":"user_agent","value":{"stringValue":"k6/0.40.0 (https://k6.io/)"}},{"key":"http.protocol","value":{"stringValue":"HTTP/1.1"}},{"key":"peer.address","value":{"stringValue":"10.16.0.16"}},{"key":"request_size","value":{"stringValue":"0"}},{"key":"response_size","value":{"stringValue":"3375"}},{"key":"component","value":{"stringValue":"proxy"}},{"key":"upstream_cluster","value":{"stringValue":"inbound|8080||"}},{"key":"upstream_cluster.name","value":{"stringValue":"inbound|8080||;"}},{"key":"http.status_code","value":{"stringValue":"500"}},{"key":"response_flags","value":{"stringValue":"-"}},{"key":"error","value":{"stringValue":"true"}},{"key":"istio.namespace","value":{"stringValue":"hipster-shop"}},{"key":"istio.canonical_service","value":{"stringValue":"frontend"}},{"key":"istio.cluster_id","value":{"stringValue":"Kubernetes"}},{"key":"istio.canonical_revision","value":{"stringValue":"1.0.0"}},{"key":"istio.mesh_id","value":{"stringValue":"cluster.local"}}],"status":{"code":2}},{"traceId":"8cd33518c063e90fe9df35d6097cd874","spanId":"3287516e3a2a339f","parentSpanId":"","name":"currencyservice.hipster-shop.svc.cluster.local:7000/*","kind":3,"startTimeUnixNano":"1748005495184355000","endTimeUnixNano":"1748005495189524000","attributes":[{"key":"node_id","value":{"stringValue":"sidecar~10.16.0.45~frontend-6b55c84d7-2wb7d.hipster-shop~hipster-shop.svc.cluster.local"}},{"key":"zone","value":{"stringValue":"europe-west3-a"}},{"key":"guid:x-request-id","value":{"stringValue":"5abf3b55-1ae1-9854-9811-3652b4afee93"}},{"key":"http.url","value":{"stringValue":"http://currencyservice:7000/hipstershop.CurrencyService/Convert"}},{"key":"http.method","value":{"stringValue":"POST"}},{"key":"downstream_cluster","value":{"stringValue":"-"}},{"key":"user_agent","value":{"stringValue":"grpc-go/1.29.1"}},{"key":"http.protocol","value":{"stringValue":"HTTP/2"}},{"key":"peer.address","value":{"stringValue":"10.16.0.45"}},{"key":"grpc.path","value":{"stringValue":"/hipstershop.CurrencyService/Convert"}},{"key":"grpc.authority","value":{"stringValue":"currencyservice:7000"}},{"key":"grpc.content_type","value":{"stringValue":"application/grpc"}},{"key":"request_size","value":{"stringValue":"25"}},{"key":"response_size","value":{"stringValue":"18"}},{"key":"component","value":{"stringValue":"proxy"}},{"key":"upstream_cluster","value":{"stringValue":"outbound|7000||currencyservice.hipster-shop.svc.cluster.local"}},{"key":"upstream_cluster.name","value":{"stringValue":"outbound|7000||currencyservice.hipster-shop.svc.cluster.local;"}},{"key":"http.status_code","value":{"stringValue":"200"}},{"key":"response_flags","value":{"stringValue":"-"}},{"key":"istio.namespace","value":{"stringValue":"hipster-shop"}},{"key":"istio.canonical_service","value":{"stringValue":"frontend"}},{"key":"istio.mesh_id","value":{"stringValue":"cluster.local"}},{"key":"istio.cluster_id","value":{"stringValue":"Kubernetes"}},{"key":"istio.canonical_revision","value":{"stringValue":"1.0.0"}},{"key":"grpc.status_code","value":{"stringValue":"0"}},{"key":"grpc.message","value":{"stringValue":"OK"}}],"status":{}}]}]}]}