{"resourceSpans":[{"resource":{"attributes":[{"key":"service.name","value":{"stringValue":"hipster-shop.hipster-shop"}}]},"scopeSpans":[{"scope":{},"spans":[{"traceId":"6e314ba060906c9bb1d265431982f4ea","spanId":"cacb030c0a4565a8","parentSpanId":"","name":"productcatalogservice.hipster-shop.svc.cluster.local:3550/*","kind":3,"startTimeUnixNano":"1748005462731720000","endTimeUnixNano":"1748005463736043000","attributes":[{"key":"node_id","value":{"stringValue":"sidecar~10.16.0.45~frontend-6b55c84d7-2wb7d.hipster-shop~hipster-shop.svc.cluster.local"}},{"key":"zone","value":{"stringValue":"europe-west3-a"}},{"key":"guid:x-request-id","value":{"stringValue":"ff06b42b-cfc1-955b-b270-1aed4738ff6c"}},{"key":"http.url","value":{"stringValue":"http://productcatalogservice:3550/hipstershop.ProductCatalogService/GetProduct"}},{"key":"http.method","value":{"stringValue":"POST"}},{"key":"downstream_cluster","value":{"stringValue":"-"}},{"key":"user_agent","value":{"stringValue":"grpc-go/1.29.1"}},{"key":"http.protocol","value":{"stringValue":"HTTP/2"}},{"key":"peer.address","value":{"stringValue":"10.16.0.45"}},{"key":"grpc.path","value":{"stringValue":"/hipstershop.ProductCatalogService/GetProduct"}},{"key":"grpc.authority","value":{"stringValue":"productcatalogservice:3550"}},{"key":"grpc.content_type","value":{"stringValue":"application/grpc"}},{"key":"request_size","value":{"stringValue":"17"}},{"key":"response_size","value":{"stringValue":"169"}},{"key":"component","value":{"stringValue":"proxy"}},{"key":"upstream_cluster","value":{"stringValue":"outbound|3550||productcatalogservice.hipster-shop.svc.cluster.local"}},{"key":"upstream_cluster.name","value":{"stringValue":"outbound|3550||productcatalogservice.hipster-shop.svc.cluster.local;"}},{"key":"http.status_code","value":{"stringValue":"200"}},{"key":"response_flags","value":{"stringValue":"-"}},{"key":"istio.canonical_revision","value":{"stringValue":"1.0.0"}},{"key":"istio.mesh_id","value":{"stringValue":"cluster.local"}},{"key":"istio.cluster_id","value":{"stringValue":"Kubernetes"}},{"key":"istio.canonical_service","value":{"stringValue":"frontend"}},{"key":"istio.namespace","value":{"stringValue":"hipster-shop"}},{"key":"grpc.status_code","value":{"stringValue":"0"}},{"key":"grpc.message","value":{"stringValue":""}}],"status":{}},{"traceId":"8abfe731532275f7a41efcbadd16abd3","spanId":"e900ad218617fa30","parentSpanId":"","name":"cartservice.hipster-shop.svc.cluster.local:7070/*","kind":3,"startTimeUnixNano":"1748005463737868000","endTimeUnixNano":"1748005463745125000","attributes":[{"key":"node_id","value":{"stringValue":"sidecar~10.16.0.45~frontend-6b55c84d7-2wb7d.hipster-shop~hipster-shop.svc.cluster.local"}},{"key":"zone","value":{"stringValue":"europe-west3-a"}},{"key":"guid:x-request-id","value":{"stringValue":"fc50a217-5ae9-9d08-b833-f560b2e35c5d"}},{"key":"http.url","value":{"stringValue":"http://cartservice:7070/hipstershop.CartService/AddItem"}},{"key":"http.method","value":{"stringValue":"POST"}},{"key":"downstream_cluster","value":{"stringValue":"-"}},{"key":"user_agent","value":{"stringValue":"grpc-go/1.29.1"}},{"key":"http.protocol","value":{"stringValue":"HTTP/2"}},{"key":"peer.address","value":{"stringValue":"10.16.0.45"}},{"key":"grpc.path","value":{"stringValue":"/hipstershop.CartService/AddItem"}},{"key":"grpc.authority","value":{"stringValue":"cartservice:7070"}},{"key":"grpc.content_type","value":{"stringValue":"application/grpc"}},{"key":"request_size","value":{"stringValue":"59"}},{"key":"response_size","value":{"stringValue":"5"}},{"key":"component","value":{"stringValue":"proxy"}},{"key":"upstream_cluster","value":{"stringValue":"outbound|7070||cartservice.hipster-shop.svc.cluster.local"}},{"key":"upstream_cluster.name","value":{"stringValue":"outbound|7070||cartservice.hipster-shop.svc.cluster.local;"}},{"key":"http.status_code","value":{"stringValue":"200"}},{"key":"response_flags","value":{"stringValue":"-"}},{"key":"istio.cluster_id","value":{"stringValue":"Kubernetes"}},{"key":"istio.canonical_service","value":{"stringValue":"frontend"}},{"key":"istio.mesh_id","value":{"stringValue":"cluster.local"}},{"key":"istio.canonical_revision","value":{"stringValue":"1.0.0"}},{"key":"istio.namespace","value":{"stringValue":"hipster-shop"}},{"key":"grpc.status_code","value":{"stringValue":"0"}}],"status":{}},{"traceId":"609089b21c0ec66cbc81d6325494e6e4","spanId":"7bfc7bfff4bb2a6d","parentSpanId":"","name":"productcatalogservice.hipster-shop.svc.cluster.local:3550/*","kind":3,"startTimeUnixNano":"1748005462744932000","endTimeUnixNano":"1748005463748625000","attributes":[{"key":"node_id","value":{"stringValue":"sidecar~10.16.0.45~frontend-6b55c84d7-2wb7d.hipster-shop~hipster-shop.svc.cluster.local"}},{"key":"zone","value":{"stringValue":"europe-west3-a"}},{"key":"guid:x-request-id","value":{"stringValue":"4f24519c-3028-91c3-a451-6323f4bacfda"}},{"key":"http.url","value":{"stringValue":"http://productcatalogservice:3550/hipstershop.ProductCatalogService/GetProduct"}},{"key":"http.method","value":{"stringValue":"POST"}},{"key":"downstream_cluster","value":{"stringValue":"-"}},{"key":"user_agent","value":{"stringValue":"grpc-go/1.29.1"}},{"key":"http.protocol","value":{"stringValue":"HTTP/2"}},{"key":"peer.address","value":{"stringValue":"10.16.0.45"}},{"key":"grpc.path","value":{"stringValue":"/hipstershop.ProductCatalogService/GetProduct"}},{"key":"grpc.authority","value":{"stringValue":"productcatalogservice:3550"}},{"key":"grpc.content_type","value":{"stringValue":"application/grpc"}},{"key":"request_size","value":{"stringValue":"17"}},{"key":"response_size","value":{"stringValue":"157"}},{"key":"component","value":{"stringValue":"proxy"}},{"key":"upstream_cluster","value":{"stringValue":"outbound|3550||productcatalogservice.hipster-shop.svc.cluster.local"}},{"key":"upstream_cluster.name","value":{"stringValue":"outbound|3550||productcatalogservice.hipster-shop.svc.cluster.local;"}},{"key":"http.status_code","value":{"stringValue":"200"}},{"key":"response_flags","value":{"stringValue":"-"}},{"key":"istio.canonical_revision","value":{"stringValue":"1.0.0"}},{"key":"istio.canonical_service","value":{"stringValue":"frontend"}},{"key":"istio.mesh_id","value":{"stringValue":"cluster.local"}},{"key":"istio.cluster_id","value":{"stringValue":"Kubernetes"}},{"key":"istio.namespace","value":{"stringValue":"hipster-shop"}},{"key":"grpc.status_code","value":{"stringValue":"0"}},{"key":"grpc.message","value":{"stringValue":""}}],"status":{}},{"traceId":"bb4a6ceb20243abd6d077b67fd0daf20","spanId":"38cf76c4bde36f70","parentSpanId":"035efd069c50f66f","name":"frontend.hipster-shop.svc.cluster.local:80/*","kind":2,"startTimeUnixNano":"1748005462729907000","endTimeUnixNano":"1748005463749336000","attributes":[{"key":"node_id","value":{"stringValue":"sidecar~10.16.0.45~frontend-6b55c84d7-2wb7d.hipster-shop~hipster-shop.svc.cluster.local"}},{"key":"zone","value":{"stringValue":"europe-west3-a"}},{"key":"guid:x-request-id","value":{"stringValue":"bee69e57-8b60-9e76-8c12-aeb65e5fd426"}},{"key":"http.url","value":{"stringValue":"http://hipstershop.34.40.36.155.nip.io/cart"}},{"key":"http.method","value":{"stringValue":"POST"}},{"key":"downstream_cluster","value":{"stringValue":"-"}},{"key":"user_agent","value":{"stringValue":"k6/0.40.0 (https://k6.io/)"}},{"key":"http.protocol","value":{"stringValue":"HTTP/1.1"}},{"key":"peer.address","value":{"stringValue":"10.16.0.16"}},{"key":"request_size","value":{"stringValue":"32"}},{"key":"response_size","value":{"stringValue":"0"}},{"key":"component","value":{"stringValue":"proxy"}},{"key":"upstream_cluster","value":{"stringValue":"inbound|8080||"}},{"key":"upstream_cluster.name","value":{"stringValue":"inbound|8080||;"}},{"key":"http.status_code","value":{"stringValue":"302"}},{"key":"response_flags","value":{"stringValue":"-"}},{"key":"istio.namespace","value":{"stringValue":"hipster-shop"}},{"key":"istio.cluster_id","value":{"stringValue":"Kubernetes"}},{"key":"istio.canonical_service","value":{"stringValue":"frontend"}},{"key":"istio.canonical_revision","value":{"stringValue":"1.0.0"}},{"key":"istio.mesh_id","value":{"stringValue":"cluster.local"}}],"status":{}},{"traceId":"588566cbf401d1e0908492a4d97666fe","spanId":"3dc157b61f23d2d2","parentSpanId":"","name":"cartservice.hipster-shop.svc.cluster.local:7070/*","kind":3,"startTimeUnixNano":"1748005463759079000","endTimeUnixNano":"1748005463764879000","attributes":[{"key":"node_id","value":{"stringValue":"sidecar~10.16.0.45~frontend-6b55c84d7-2wb7d.hipster-shop~hipster-shop.svc.cluster.local"}},{"key":"zone","value":{"stringValue":"europe-west3-a"}},{"key":"guid:x-request-id","value":{"stringValue":"c8a65bb0-ec27-92d1-be6f-2dc799c18c6b"}},{"key":"http.url","value":{"stringValue":"http://cartservice:7070/hipstershop.CartService/GetCart"}},{"key":"http.method","value":{"stringValue":"POST"}},{"key":"downstream_cluster","value":{"stringValue":"-"}},{"key":"user_agent","value":{"stringValue":"grpc-go/1.29.1"}},{"key":"http.protocol","value":{"stringValue":"HTTP/2"}},{"key":"peer.address","value":{"stringValue":"10.16.0.45"}},{"key":"grpc.path","value":{"stringValue":"/hipstershop.CartService/GetCart"}},{"key":"grpc.authority","value":{"stringValue":"cartservice:7070"}},{"key":"grpc.content_type","value":{"stringValue":"application/grpc"}},{"key":"request_size","value":{"stringValue":"43"}},{"key":"response_size","value":{"stringValue":"5"}},{"key":"component","value":{"stringValue":"proxy"}},{"key":"upstream_cluster","value":{"stringValue":"outbound|7070||cartservice.hipster-shop.svc.cluster.local"}},{"key":"upstream_cluster.name","value":{"stringValue":"outbound|7070||cartservice.hipster-shop.svc.cluster.local;"}},{"key":"http.status_code","value":{"stringValue":"200"}},{"key":"response_flags","value":{"stringValue":"-"}},{"key":"istio.cluster_id","value":{"stringValue":"Kubernetes"}},{"key":"istio.namespace","value":{"stringValue":"hipster-shop"}},{"key":"istio.mesh_id","value":{"stringValue":"cluster.local"}},{"key":"istio.canonical_service","value":{"stringValue":"frontend"}},{"key":"istio.canonical_revision","value":{"stringValue":"1.0.0"}},{"key":"grpc.status_code","value":{"stringValue":"0"}}],"status":{}}]}]}]}