{"resourceSpans":[{"resource":{"attributes":[{"key":"service.name","value":{"stringValue":"istio-ingressgateway.istio-system"}}]},"scopeSpans":[{"scope":{},"spans":[{"traceId":"2fcc6b838ed3fd5aa0da18a13cdfab69","spanId":"5139a7523fd1566a","parentSpanId":"","name":"frontend.hipster-shop.svc.cluster.local:80/*","kind":3,"startTimeUnixNano":"1748005386191923000","endTimeUnixNano":"1748005386227364000","attributes":[{"key":"node_id","value":{"stringValue":"router~10.16.0.16~istio-ingressgateway-5668d9bd66-k9qlf.istio-system~istio-system.svc.cluster.local"}},{"key":"zone","value":{"stringValue":"europe-west3-a"}},{"key":"guid:x-request-id","value":{"stringValue":"044644a6-67ba-971c-aaaf-901e053cb9b1"}},{"key":"http.url","value":{"stringValue":"http://hipstershop.34.40.36.155.nip.io/cart"}},{"key":"http.method","value":{"stringValue":"GET"}},{"key":"downstream_cluster","value":{"stringValue":"-"}},{"key":"user_agent","value":{"stringValue":"k6/0.40.0 (https://k6.io/)"}},{"key":"http.protocol","value":{"stringValue":"HTTP/1.1"}},{"key":"peer.address","value":{"stringValue":"10.16.0.1"}},{"key":"request_size","value":{"stringValue":"0"}},{"key":"response_size","value":{"stringValue":"3375"}},{"key":"component","value":{"stringValue":"proxy"}},{"key":"upstream_cluster","value":{"stringValue":"outbound|80||frontend.hipster-shop.svc.cluster.local"}},{"key":"upstream_cluster.name","value":{"stringValue":"outbound|80||frontend.hipster-shop.svc.cluster.local;"}},{"key":"http.status_code","value":{"stringValue":"500"}},{"key":"response_flags","value":{"stringValue":"-"}},{"key":"error","value":{"stringValue":"true"}},{"key":"istio.cluster_id","value":{"stringValue":"Kubernetes"}},{"key":"istio.canonical_service","value":{"stringValue":"istio-ingressgateway"}},{"key":"istio.canonical_revision","value":{"stringValue":"latest"}},{"key":"istio.mesh_id","value":{"stringValue":"cluster.local"}},{"key":"istio.namespace","value":{"stringValue":"istio-system"}}],"status":{"code":2}},{"traceId":"a3c95c22ae1292ca2fb290231f90b1c9","spanId":"cb53340a8375cbd0","parentSpanId":"","name":"frontend.hipster-shop.svc.cluster.local:80/*","kind":3,"startTimeUnixNano":"1748005385249804000","endTimeUnixNano":"1748005386319927000","attributes":[{"key":"node_id","value":{"stringValue":"router~10.16.0.16~istio-ingressgateway-5668d9bd66-k9qlf.istio-system~istio-system.svc.cluster.local"}},{"key":"zone","value":{"stringValue":"europe-west3-a"}},{"key":"guid:x-request-id","value":{"stringValue":"12124b10-ba8a-9045-85d2-ff7a92b600a7"}},{"key":"http.url","value":{"stringValue":"http://hipstershop.34.40.36.155.nip.io/product/9SIQT8TOJO"}},{"key":"http.method","value":{"stringValue":"GET"}},{"key":"downstream_cluster","value":{"stringValue":"-"}},{"key":"user_agent","value":{"stringValue":"k6/0.40.0 (https://k6.io/)"}},{"key":"http.protocol","value":{"stringValue":"HTTP/1.1"}},{"key":"peer.address","value":{"stringValue":"10.16.0.1"}},{"key":"request_size","value":{"stringValue":"0"}},{"key":"response_size","value":{"stringValue":"3374"}},{"key":"component","value":{"stringValue":"proxy"}},{"key":"upstream_cluster","value":{"stringValue":"outbound|80||frontend.hipster-shop.svc.cluster.local"}},{"key":"upstream_cluster.name","value":{"stringValue":"outbound|80||frontend.hipster-shop.svc.cluster.local;"}},{"key":"http.status_code","value":{"stringValue":"500"}},{"key":"response_flags","value":{"stringValue":"-"}},{"key":"error","value":{"stringValue":"true"}},{"key":"istio.namespace","value":{"stringValue":"istio-system"}},{"key":"istio.cluster_id","value":{"stringValue":"Kubernetes"}},{"key":"istio.canonical_service","value":{"stringValue":"istio-ingressgateway"}},{"key":"istio.canonical_revision","value":{"stringValue":"latest"}},{"key":"istio.mesh_id","value":{"stringValue":"cluster.local"}}],"status":{"code":2}},{"traceId":"eac479385ff64966575b2e96112a855d","spanId":"41c8d786f08cf67d","parentSpanId":"98e9debe8526c5a2","name":"opentelemetry-demo-frontend.otel-demo.svc.cluster.local:8080/*","kind":3,"startTimeUnixNano":"1748005386378412000","endTimeUnixNano":"1748005386378988000","attributes":[{"key":"node_id","value":{"stringValue":"router~10.16.0.16~istio-ingressgateway-5668d9bd66-k9qlf.istio-system~istio-system.svc.cluster.local"}},{"key":"zone","value":{"stringValue":"europe-west3-a"}},{"key":"guid:x-request-id","value":{"stringValue":"a5965591-be0e-9c96-968b-48247756005b"}},{"key":"http.url","value":{"stringValue":"http://oteldemo.34.40.36.155.nip.io/api/products/2ZYFJ3GM2N"}},{"key":"http.method","value":{"stringValue":"GET"}},{"key":"downstream_cluster","value":{"stringValue":"-"}},{"key":"user_agent","value":{"stringValue":"python-requests/2.31.0"}},{"key":"http.protocol","value":{"stringValue":"HTTP/1.1"}},{"key":"peer.address","value":{"stringValue":"10.16.0.1"}},{"key":"request_size","value":{"stringValue":"0"}},{"key":"response_size","value":{"stringValue":"19"}},{"key":"component","value":{"stringValue":"proxy"}},{"key":"upstream_cluster","value":{"stringValue":"outbound|8080||opentelemetry-demo-frontend.otel-demo.svc.cluster.local"}},{"key":"upstream_cluster.name","value":{"stringValue":"outbound|8080||opentelemetry-demo-frontend.otel-demo.svc.cluster.local;"}},{"key":"http.status_code","value":{"stringValue":"503"}},{"key":"response_flags","value":{"stringValue":"UH"}},{"key":"error","value":{"stringValue":"true"}},{"key":"istio.namespace","value":{"stringValue":"istio-system"}},{"key":"istio.cluster_id","value":{"stringValue":"Kubernetes"}},{"key":"istio.canonical_service","value":{"stringValue":"istio-ingressgateway"}},{"key":"istio.canonical_revision","value":{"stringValue":"latest"}},{"key":"istio.mesh_id","value":{"stringValue":"cluster.local"}}],"status":{"code":2}},{"traceId":"00c88261fe7cb35225b89df26c8bc19d","spanId":"b2d358dc30383a87","parentSpanId":"","name":"frontend.hipster-shop.svc.cluster.local:80/*","kind":3,"startTimeUnixNano":"1748005386354010000","endTimeUnixNano":"1748005386391033000","attributes":[{"key":"node_id","value":{"stringValue":"router~10.16.0.16~istio-ingressgateway-5668d9bd66-k9qlf.istio-system~istio-system.svc.cluster.local"}},{"key":"zone","value":{"stringValue":"europe-west3-a"}},{"key":"guid:x-request-id","value":{"stringValue":"af388d85-ec48-9fab-9ac4-7cfdb66f7f63"}},{"key":"http.url","value":{"stringValue":"http://hipstershop.34.40.36.155.nip.io/cart"}},{"key":"http.method","value":{"stringValue":"GET"}},{"key":"downstream_cluster","value":{"stringValue":"-"}},{"key":"user_agent","value":{"stringValue":"k6/0.40.0 (https://k6.io/)"}},{"key":"http.protocol","value":{"stringValue":"HTTP/1.1"}},{"key":"peer.address","value":{"stringValue":"10.16.0.1"}},{"key":"request_size","value":{"stringValue":"0"}},{"key":"response_size","value":{"stringValue":"3375"}},{"key":"component","value":{"stringValue":"proxy"}},{"key":"upstream_cluster","value":{"stringValue":"outbound|80||frontend.hipster-shop.svc.cluster.local"}},{"key":"upstream_cluster.name","value":{"stringValue":"outbound|80||frontend.hipster-shop.svc.cluster.local;"}},{"key":"http.status_code","value":{"stringValue":"500"}},{"key":"response_flags","value":{"stringValue":"-"}},{"key":"error","value":{"stringValue":"true"}},{"key":"istio.mesh_id","value":{"stringValue":"cluster.local"}},{"key":"istio.cluster_id","value":{"stringValue":"Kubernetes"}},{"key":"istio.canonical_service","value":{"stringValue":"istio-ingressgateway"}},{"key":"istio.canonical_revision","value":{"stringValue":"latest"}},{"key":"istio.namespace","value":{"stringValue":"istio-system"}}],"status":{"code":2}},{"traceId":"aa72a5567236d1d40aad07773d61d499","spanId":"5c707e8ff257b610","parentSpanId":"","name":"frontend.hipster-shop.svc.cluster.local:80/*","kind":3,"startTimeUnixNano":"1748005385341363000","endTimeUnixNano":"1748005386408529000","attributes":[{"key":"node_id","value":{"stringValue":"router~10.16.0.16~istio-ingressgateway-5668d9bd66-k9qlf.istio-system~istio-system.svc.cluster.local"}},{"key":"zone","value":{"stringValue":"europe-west3-a"}},{"key":"guid:x-request-id","value":{"stringValue":"fbcbd4bc-3407-9b1c-b87c-4572c60bb097"}},{"key":"http.url","value":{"stringValue":"http://hipstershop.34.40.36.155.nip.io/product/OLJCESPC7Z"}},{"key":"http.method","value":{"stringValue":"GET"}},{"key":"downstream_cluster","value":{"stringValue":"-"}},{"key":"user_agent","value":{"stringValue":"k6/0.40.0 (https://k6.io/)"}},{"key":"http.protocol","value":{"stringValue":"HTTP/1.1"}},{"key":"peer.address","value":{"stringValue":"10.16.0.1"}},{"key":"request_size","value":{"stringValue":"0"}},{"key":"response_size","value":{"stringValue":"3374"}},{"key":"component","value":{"stringValue":"proxy"}},{"key":"upstream_cluster","value":{"stringValue":"outbound|80||frontend.hipster-shop.svc.cluster.local"}},{"key":"upstream_cluster.name","value":{"stringValue":"outbound|80||frontend.hipster-shop.svc.cluster.local;"}},{"key":"http.status_code","value":{"stringValue":"500"}},{"key":"response_flags","value":{"stringValue":"-"}},{"key":"error","value":{"stringValue":"true"}},{"key":"istio.mesh_id","value":{"stringValue":"cluster.local"}},{"key":"istio.cluster_id","value":{"stringValue":"Kubernetes"}},{"key":"istio.canonical_service","value":{"stringValue":"istio-ingressgateway"}},{"key":"istio.canonical_revision","value":{"stringValue":"latest"}},{"key":"istio.namespace","value":{"stringValue":"istio-system"}}],"status":{"code":2}}]}]}]}